cpx/__init__.py
cpx/__main__.py
cpx/extraction/.gitkeep
cpx/filters/__init__.py
cpx/filters/_btype.py
cpx/filters/nan.py
cpx/filters/parallel.py
cpx/filters/spatial.py
cpx/filters/temporal.py
cpx/filters/utils.py
cpx/io/__init__.py
cpx/io/_exceptions.py
cpx/io/tiff.py
cpx/io/utils.py
cpx/io/validation.py
cpx/io/video.py
cpx/metrics/__init__.py
cpx/metrics/local_correlation.py
cpx/metrics/pnr.py
cpx/py.typed
cpx/registration/__init__.py
cpx/registration/_numerics.py
cpx/registration/model.py
cpx/registration/rigid.py
cpx/utils/__init__.py
cpx/utils/info.py
cpx/utils/notebook.py
cpx/utils/utils.py
cpx-0.0.1.dist-info/LICENSE.txt
cpx-0.0.1.dist-info/METADATA
cpx-0.0.1.dist-info/WHEEL
cpx-0.0.1.dist-info/RECORD
