Metadata-Version: 2.1
Name: cpx
Version: 0.0.1
Summary: 
Author: Ryan Peters
Author-email: RyanIRL@icloud.com
Requires-Python: >=3.7,<4.0
Classifier: Development Status :: 2 - Pre-Alpha
Classifier: Programming Language :: Python :: 3
Classifier: Programming Language :: Python :: 3.7
Classifier: Programming Language :: Python :: 3.8
Classifier: Programming Language :: Python :: 3.9
Classifier: Programming Language :: Python :: 3.10
Classifier: Programming Language :: Python :: 3.11
Requires-Dist: joblib
Requires-Dist: matplotlib
Requires-Dist: numpy (>=1.20)
Requires-Dist: opencv-python-headless
Requires-Dist: psutil
Requires-Dist: scikit-image
Requires-Dist: scikit-learn
Requires-Dist: scipy
Requires-Dist: tifffile
Requires-Dist: tqdm
